yekta_metrics/__init__.py
yekta_metrics/config.py
yekta_metrics/prometheus.py
yekta_metrics-2.3.8.dist-info/WHEEL
yekta_metrics-2.3.8.dist-info/METADATA
yekta_metrics-2.3.8.dist-info/RECORD
