Metadata-Version: 2.1
Name: yekta-metrics
Version: 2.3.8
Summary: Yektanet Metrics Module
Author: Sadegh Hayeri
Author-email: hayerisadegh@gmail.com
Requires-Python: >=3,<4
Classifier: Programming Language :: Python :: 3
Classifier: Programming Language :: Python :: 3.4
Classifier: Programming Language :: Python :: 3.5
Classifier: Programming Language :: Python :: 3.6
Classifier: Programming Language :: Python :: 3.7
Classifier: Programming Language :: Python :: 3.8
Classifier: Programming Language :: Python :: 3.9
Requires-Dist: prometheus-client (>=0.9.0,<0.10.0)
